ariadne_lambda/__init__.py
ariadne_lambda/base.py
ariadne_lambda/graphql.py
ariadne_lambda/http_handler.py
ariadne_lambda/schema.py
ariadne_lambda-0.3.1.dist-info/METADATA
ariadne_lambda-0.3.1.dist-info/WHEEL
ariadne_lambda-0.3.1.dist-info/licenses/LICENSE
ariadne_lambda-0.3.1.dist-info/RECORD
