Metadata-Version: 2.3
Name: ariadne-lambda
Version: 0.3.1
Summary: This package extends the Ariadne library by adding a GraphQL HTTP handler designed for use in AWS Lambda environments.
Project-URL: Documentation, https://github.com/mirumee/ariadne-lambda#readme
Project-URL: Issues, https://github.com/mirumee/ariadne-lambda/issues
Project-URL: Source, https://github.com/mirumee/ariadne-lambda
Author-email: Mirumee Software <it@mirumee.com>
License: BSD 3-Clause License
License-File: LICENSE
Classifier: Development Status :: 4 - Beta
Classifier: Intended Audience :: Developers
Classifier: License :: OSI Approved :: BSD License
Classifier: Operating System :: OS Independent
Classifier: Programming Language :: Python
Classifier: Programming Language :: Python :: 3.8
Classifier: Programming Language :: Python :: 3.9
Classifier: Programming Language :: Python :: 3.10
Classifier: Programming Language :: Python :: 3.11
Classifier: Programming Language :: Python :: 3.12
Classifier: Programming Language :: Python :: Implementation :: CPython
Classifier: Programming Language :: Python :: Implementation :: PyPy
Requires-Python: >=3.8
Requires-Dist: ariadne<0.24.0,>=0.23.0
Requires-Dist: aws-lambda-powertools<3.0.0,>=2.35.1
Requires-Dist: jmespath
Requires-Dist: pydantic<3.0.0,>=2.4.0
